odoo10_addon_sale_commercial_partner-10.0.1.0.2-py3.8-nspkg.pth
odoo/addons/sale_commercial_partner/README.rst
odoo/addons/sale_commercial_partner/__init__.py
odoo/addons/sale_commercial_partner/__manifest__.py
odoo/addons/sale_commercial_partner/i18n/ca.po
odoo/addons/sale_commercial_partner/i18n/de.po
odoo/addons/sale_commercial_partner/i18n/el_GR.po
odoo/addons/sale_commercial_partner/i18n/es.po
odoo/addons/sale_commercial_partner/i18n/es_ES.po
odoo/addons/sale_commercial_partner/i18n/es_VE.po
odoo/addons/sale_commercial_partner/i18n/fi.po
odoo/addons/sale_commercial_partner/i18n/fr.po
odoo/addons/sale_commercial_partner/i18n/hr.po
odoo/addons/sale_commercial_partner/i18n/hr_HR.po
odoo/addons/sale_commercial_partner/i18n/hu.po
odoo/addons/sale_commercial_partner/i18n/it.po
odoo/addons/sale_commercial_partner/i18n/nl.po
odoo/addons/sale_commercial_partner/i18n/nl_NL.po
odoo/addons/sale_commercial_partner/i18n/pt.po
odoo/addons/sale_commercial_partner/i18n/pt_BR.po
odoo/addons/sale_commercial_partner/i18n/ro.po
odoo/addons/sale_commercial_partner/i18n/sale_commercial_partner.pot
odoo/addons/sale_commercial_partner/i18n/sk.po
odoo/addons/sale_commercial_partner/i18n/sl.po
odoo/addons/sale_commercial_partner/i18n/tr.po
odoo/addons/sale_commercial_partner/i18n/tr_TR.po
odoo/addons/sale_commercial_partner/i18n/vi_VN.po
odoo/addons/sale_commercial_partner/i18n/zh_CN.po
odoo/addons/sale_commercial_partner/models/__init__.py
odoo/addons/sale_commercial_partner/models/sale.py
odoo/addons/sale_commercial_partner/static/description/icon.png
odoo/addons/sale_commercial_partner/views/sale.xml
odoo10_addon_sale_commercial_partner-10.0.1.0.2.dist-info/METADATA
odoo10_addon_sale_commercial_partner-10.0.1.0.2.dist-info/WHEEL
odoo10_addon_sale_commercial_partner-10.0.1.0.2.dist-info/namespace_packages.txt
odoo10_addon_sale_commercial_partner-10.0.1.0.2.dist-info/top_level.txt
odoo10_addon_sale_commercial_partner-10.0.1.0.2.dist-info/RECORD
